zigzag/__init__.py
zigzag_cython/__init__.py
zigzag_cython/core.c
zigzag_cython/core.cpython-312-darwin.so
zigzag_cython/core.pyx
zigzag_cython/plotting.py
slow_zigzag-0.3.13.dist-info/METADATA
slow_zigzag-0.3.13.dist-info/WHEEL
slow_zigzag-0.3.13.dist-info/top_level.txt
slow_zigzag-0.3.13.dist-info/RECORD
