Metadata-Version: 2.4
Name: slow_zigzag
Version: 0.3.13
Summary: Zig Zag indicator
Home-page: https://github.com/pakchu/zigzag
Author: ['hjkim17', 'pakchu']
Classifier: Programming Language :: Python :: 3.9
Classifier: Programming Language :: Python :: 3.10
Classifier: Programming Language :: Python :: 3.11
Classifier: Programming Language :: Python :: 3.12
Requires-Python: >=3.9
Requires-Dist: numpy
Requires-Dist: pandas
Requires-Dist: cython
Dynamic: author
Dynamic: classifier
Dynamic: description
Dynamic: home-page
Dynamic: requires-dist
Dynamic: requires-python
Dynamic: summary
